CHANGES.txt
LICENSE.txt
MANIFEST.in
README.txt
setup.py
EStruct.egg-info/PKG-INFO
EStruct.egg-info/SOURCES.txt
EStruct.egg-info/dependency_links.txt
EStruct.egg-info/requires.txt
EStruct.egg-info/top_level.txt
bin/estruct_example.py
estruct/__init__.py
estruct/estruct.py
estruct/tests/__init__.py
estruct/tests/estruct_test.py