Metadata-Version: 1.1
Name: EStruct
Version: 0.1.3
Summary: Python package to extend the capabilities of the standard library's Struct package.
Home-page: http://pypi.python.org/pypi/EStruct/
Author: Simon Black
Author-email: simon.black.bug@gmail.com
License: LICENSE.txt
Platform: UNKNOWN
Classifier: Programming Language :: Python
Classifier: Topic :: Software Development :: Libraries :: Python Modules
